COPYING.txt
MANIFEST.in
README.txt
setup.py
bae/__init__.py
bae/errors.py
bae.egg-info/PKG-INFO
bae.egg-info/SOURCES.txt
bae.egg-info/dependency_links.txt
bae.egg-info/not-zip-safe
bae.egg-info/requires.txt
bae.egg-info/top_level.txt
bae/cli/Auth_tools.py
bae/cli/__init__.py
bae/cli/client.py
bae/cli/code_tool.py
bae/cli/messages.py
bae/config/__init__.py
bae/config/config.py
bae/config/constants.py
bae/config/parser.py
bae/rest/__init__.py
bae/rest/rest.py
bae/rest/test/__init__.py
bae/rest/test/test_rest.py
bin/bae