Metadata-Version: 1.1
Name: bae
Version: 2.0.7
Summary: A BAE Client Tool
Home-page: http://developer.baidu.com
Author: Zhang Guanxing
Author-email: zhangguanxing01@baidu.com
License: UNKNOWN
Keywords: bae client tool
Platform: UNKNOWN
Classifier: Development Status :: 4 - Beta
Classifier: Topic :: Utilities
Classifier: Programming Language :: Python :: 2 :: Only
